{
  "required": true,
  "package": "cn.hanabi.injection.mixins",
  "refmap": "mixins.hanabi.refmap.json",
  "compatibilityLevel": "JAVA_8",
  "mixins": [
    "MixinBlock",
    "MixinBlockModelRenderer",
    "MixinBlockRendererDispatcher",
    "MixinBlockStairs",
    "MixinC00PacketKeepAlive",
    "MixinC01PacketChatMessage",
    "MixinC03PacketPlayer",
    "MixinC0FPacketConfirmTransaction",
    "MixinC10PacketCreativeInventoryAction",
    "MixinDefaultPlayerSkin",
    "MixinEntity",
    "MixinEntityLivingBase",
    "MixinEntityPlayer",
    "MixinEntityPlayerSP",
    "MixinEntityRenderer",
    "MixinFontRenderer",
    "MixinGuiChat",
    "MixinGuiChest",
    "MixinGuiDisconnected",
    "MixinGuiIngame",
    "MixinGuiMainMenu",
    "MixinGuiNewChat",
    "MixinGuiPlayerTabOverlay",
    "MixinGuiScreen",
    "MixinGuiSpectator",
    "MixinItemRenderer",
    "MixinItemSword",
    "MixinItemTools",
    "MixinKeyBinding",
    "MixinMinecraft",
    "MixinMovementInput",
    "MixinMovementInputFromOptions",
    "MixinNetworkManager",
    "MixinNetworkManagerChInit",
    "MixinPlayerControllerMP",
    "MixinRender",
    "MixinRenderer",
    "MixinRendererLivingEntity",
    "MixinRenderManager",
    "MixinS02PacketChat",
    "MixinS05PacketSpawnPosition",
    "MixinS08PacketPlayerPosLook",
    "MixinS12PacketEntityVelocity",
    "MixinS19PacketEntityStatus",
    "MixinS27PacketExplosion",
    "MixinS32PacketConfirmTransaction",
    "MixinShaderGroup",
    "MixinStatList",
    "MixinVisGraph",
    "MixinWorld",
    "MixinWorldRenderer"
  ],
  "client": [
    "MixinAbstractClientPlayer",
    "MixinGui",
    "MixinGuiConnecting1"
  ]
}